swaggergen_api/__init__.py
swaggergen_api/__main__.py
swaggergen_api/_version.py
swaggergen_api/loader_swagger.py
swaggergen_api/swagger_generate.py
swaggergen_api/templates/api.tpl
swaggergen_api_object-1.0.0.dist-info/METADATA
swaggergen_api_object-1.0.0.dist-info/WHEEL
swaggergen_api_object-1.0.0.dist-info/entry_points.txt
swaggergen_api_object-1.0.0.dist-info/top_level.txt
swaggergen_api_object-1.0.0.dist-info/RECORD
