Metadata-Version: 2.1
Name: swaggergen-api-object
Version: 1.0.0
Summary: Generate API Object from Swagger docs.
Home-page: UNKNOWN
Author: CHNJX
Author-email: 360088940@qq.com
License: UNKNOWN
Platform: UNKNOWN
Requires-Dist: click (==8.1.3)
Requires-Dist: Jinja2 (==3.1.2)
Requires-Dist: MarkupSafe (==2.1.2)
Requires-Dist: PyYAML (==6.0)
Requires-Dist: six (==1.16.0)
